pyleague/__init__.py
pyleague/domain/__init__.py
pyleague/domain/day_pointer.py
pyleague/domain/groups_per_day.py
pyleague/domain/participants.py
pyleague/entrypoint/__init__.py
pyleague/entrypoint/main.py
pyleague/files/day_pointer.json
pyleague/files/groups_per_day.json
pyleague/files/participants.json
pyleague/infrastructure/__init__.py
pyleague/infrastructure/path_utils.py
pyleague/tests/__init__.py
pyleague/tests/test_pyleague.py
pyleague/use_cases/__init__.py
pyleague/use_cases/init.py
pyleague/use_cases/next.py
pyleague/use_cases/participants.py
pyleague/use_cases/previous.py
pyleague/use_cases/today.py
pyleague-0.2.0.dist-info/entry_points.txt
pyleague-0.2.0.dist-info/WHEEL
pyleague-0.2.0.dist-info/METADATA
pyleague-0.2.0.dist-info/RECORD
