Metadata-Version: 2.1
Name: pyleague
Version: 0.2.0
Summary: Pyleague is a cli tool that helps organizing competitions. After providing pyleague with a list of the competition's participants you will be able to get the matches for each day of the competition.
Home-page: https://github.com/mf-andres/pyleague
Author: mf-andres
Author-email: amunoz@gradiant.org
Requires-Python: >=3.9,<4.0
Classifier: Programming Language :: Python :: 3
Classifier: Programming Language :: Python :: 3.9
Classifier: Programming Language :: Python :: 3.10
Classifier: Programming Language :: Python :: 3.11
Requires-Dist: typer (>=0.7.0,<0.8.0)
Project-URL: Repository, https://github.com/mf-andres/pyleague
